codr/__init__.py
codr/cli.py
codr/codr.py
codr-0.1.0.dist-info/entry_points.txt
codr-0.1.0.dist-info/WHEEL
codr-0.1.0.dist-info/METADATA
codr-0.1.0.dist-info/RECORD
